stenographer/__init__.py
stenographer/__main__.py
stenographer/__version__.py
stenographer/agent.py
stenographer/cassette.py
stenographer/proxy.py
stenographer/test/__init__.py
stenographer/test/helpers.py
stenographer/test/test_agent.py
stenographer/test/test_cassette.py
stenographer/test/test_proxy.py
stenographer/test/fixtures/cassettes/room208.json
stenographer-0.1.3.dist-info/DESCRIPTION.rst
stenographer-0.1.3.dist-info/METADATA
stenographer-0.1.3.dist-info/metadata.json
stenographer-0.1.3.dist-info/RECORD
stenographer-0.1.3.dist-info/top_level.txt
stenographer-0.1.3.dist-info/WHEEL
