Metadata-Version: 2.0
Name: stenographer
Version: 0.1.3
Summary: An HTTP interaction recorder for Twisted Web
Home-page: https://github.com/kxz/stenographer
Author: Kevin Xiwei Zheng
Author-email: kxz+stenographer@room208.org
License: X11
Platform: UNKNOWN
Classifier: Development Status :: 2 - Pre-Alpha
Classifier: Framework :: Twisted
Classifier: Intended Audience :: Developers
Classifier: License :: OSI Approved :: MIT License
Classifier: Operating System :: OS Independent
Classifier: Programming Language :: Python :: 2
Classifier: Programming Language :: Python :: 2.7
Classifier: Programming Language :: Python :: 2 :: Only
Classifier: Topic :: Internet :: WWW/HTTP
Classifier: Topic :: Software Development :: Testing
Requires-Dist: Twisted (>=14.0.0)
